{
    "name": "Moonlit Allure",
    "description": "Increases arousal dealt by 20%, critical chance and out of stance evade chance by 10%, and initiative by 5. But increases item drop chance and eros dropped by 20%, and gives 10% more exp on victory.",

    "LevelReq": "0",
    "PerkReq": [ ""],
    "StatReq": [ ""],
    "StatReqAmount": [ "0"],

    "PerkType": [  "StatusIcon",                         "DamageBoost",    "InitiativeBonus",    "CritChanceBoost", "OutOfStanceEvade", "ItemDropChance",  "ErosBoost", "ExpBoost"],
    "EffectPower": [ "StatusIcons/AllureofTheNight.png",         "20",            "5",               "10",              "10",                 "20",             "20",           "10"],

    "PlayerCanPurchase": "No"
}
