{
    "name": "Escape Artist",
    "description": "Become more elusive, increasing the chance of getting out of stances by 20%, your ability to break out of restraints by 20%, and your chance to successfully run away from fights by 20%!",

    "LevelReq": "0",
    "PerkReq": [ "Swift"],
    "StatReq": [ "Technique"],
    "StatReqAmount": [ "20"],

    "PerkType": [ "GetOutOfStance", "RemoveRestraints", "RunChance"],
    "EffectPower": [ "20",                  "20",               "20"],

    "PlayerCanPurchase": "Yes"
}
