{
    "IDname": "",
    "Addition": "Yes",
    "skillList": [
        ""
    ],
    "perks": [ ""],
    "ItemDropList": [
        {
            "name": "",
            "dropChance": ""
        }
    ],
    "lossScenes": [
        {
            "NameOfScene": "",
            "move": "",
            "stance": "",
            "includes": [ ""],
            "theScene": [
            ""
            ],
            "picture": ""
        }
    ],
    "combatDialogue": [
        {
            "lineTrigger": "",
            "move": "",
            "theText": [
            ""
            ]
        }
    ],
    "victoryScenes": [
        {
            "NameOfScene": "",
            "move": "",
            "stance": "",
            "includes": [ ""],
            "theScene": [
            ""
            ],
            "picture": ""
        }
    ],
    "pictures": [

    ]
}
