{
    "name": "Forest Dungeon",
    "exploreTitle": "Forest Dungeon",
    "requires": [ "Vandal Note"],
    "FullyUnlockedBy": [ "Sigil Of Allure"],
    "MusicList": [ "music/Forest Dungeon/Stalwick-_Forest_Dungeon-Lurking.mp3"],
    "mapIcon": "map/MGD_Map_Icon_ForestTower",
    "mapIconXpos": "1076",
    "mapIconYpos": "734",
    "mapIconZorder": "2",
    "mapClouds": "map/map_dungeon_clouds.png",
    "mapCloudsXpos": "0",
    "mapCloudsYpos": "0",
    "MinimumDeckSize": "8",
    "MaximumMonsterDeck": "8",
    "MaximumEventDeck": "6",
    "Monsters": [ "Imp", "Matango", "Blue Slime", "Phantasmal Vili PuffPuff", "Phantasmal Vili Titfuck"],
    "MonsterGroups": [
                  {
                      "Group": [ "Imp", "Imp", "Imp"]
                  },
                  {
                      "Group": [ "Imp", "Imp"]
                  },
                  {
                      "Group": [ "Imp", "Imp"]
                  },
                  {
                      "Group": [ "Imp", "Imp"]
                  },
                  {
                      "Group": [ "Imp"]
                  },
                  {
                      "Group": [ "Matango"]
                  },
                  {
                      "Group": [ "Matango"]
                  },
                  {
                      "Group": [ "Matango"]
                  },
                  {
                      "Group": [ "Blue Slime"]
                  },
                  {
                      "Group": [ "Blue Slime"]
                  },
                  {
                      "Group": [ "Blue Slime"]
                  },
                  {
                      "Group": [ "Phantasmal Vili PuffPuff"]
                  },
                  {
                      "Group": [ "Phantasmal Vili PuffPuff", "Phantasmal Vili PuffPuff"]
                  },
                  {
                      "Group": [ "Phantasmal Vili Titfuck", "Phantasmal Vili PuffPuff"]
                  },
                  {
                      "Group": [ "Phantasmal Vili Titfuck", "Phantasmal Vili Titfuck"]
                  },
                  {
                      "Group": [ "Phantasmal Vili Titfuck"]
                  }


                ],
    "Events": [ "Mimics", "Golden Mimics", "Bag Mimic", "Imp Den", "Imp Glory Hole", "Matango Ambush", "Commander's Pet", "Maid on Duty", "Remote Room", "Matango Den", "Puff Puff Parlour", "Arch-Imp Glory Hole", "Vili's Booby Trap", "Vili's Dreamy Encounter", "Trapped Titfuck Room" ],
    "Quests": [ "Vili the Titillating Terror"],
    "Adventures": [ "Forest Dungeon", "Visit Sofia's Domain", "Vili's Trial of Titties!"],
    "Treasure": [
                  {
                      "Common": [ "Calming Potion", "Insomnia Potion", "Ugli Herb"]
                  },
                  {
                      "Uncommon": [ "Calming Potion", "Energy Potion", "Insomnia Potion", "Insomnia Rune", "Stoic Rune", "Luck Rune", "Soothing Potion"]
                  },
                  {
                      "Rare": [ "Panacea", "Luck Rune", "Insomnia Rune", "Gloves of Skill", "Cock Ring of Justice", "Power Belt"]
                  }
              ],
    "Eros": [
                {
                    "Common": "100"
                },
                {
                    "Uncommon": "150"
                },
                {
                    "Rare": "250"
                }
            ],
    "picture": "DungeonForest.png"
}
